DiscoNet/__init__.py
DiscoNet/__main__.py
DiscoNet/_freezesupport.py
DiscoNet/_platform_detect.py
DiscoNet/disco-1024.png
DiscoNet/disco-256.png
DiscoNet/disco.icns
DiscoNet/disco.ico
DiscoNet/discoveryscan.py
DiscoNet-0.3.0.dist-info/DESCRIPTION.rst
DiscoNet-0.3.0.dist-info/METADATA
DiscoNet-0.3.0.dist-info/RECORD
DiscoNet-0.3.0.dist-info/WHEEL
DiscoNet-0.3.0.dist-info/entry_points.txt
DiscoNet-0.3.0.dist-info/metadata.json
DiscoNet-0.3.0.dist-info/top_level.txt
