Metadata-Version: 2.0
Name: DiscoNet
Version: 0.3.0
Summary: A tool for automating network discovery.
Home-page: https://github.com/jasmas/DiscoNet
Author: Jason Masker
Author-email: masker@post.harvard.edu
License: MIT
Keywords: net network discovery excel xlsx scan scanner tool subnet ip
Platform: UNKNOWN
Requires-Dist: docutils (>=0.3)
Requires-Dist: future (>=0.16.0)
Requires-Dist: openpyxl (>=2.4.1)
Requires-Dist: paramiko (>=2.1.1)
Requires-Dist: pypiwin32 (>=219); sys_platform=="win32"
Requires-Dist: winshell (>=0.6); sys_platform=="win32"
Provides-Extra: kivy
Requires-Dist: kivy (>=1.9.0); extra == 'kivy'
Provides-Extra: kivy
Requires-Dist: kivy.deps.glew (>=0.1.4); sys_platform=="win32" and extra == 'kivy'
Requires-Dist: kivy.deps.sdl2 (>=0.1.12); sys_platform=="win32" and extra == 'kivy'
